inigrep/__init__.py
inigrep/__main__.py
inigrep/_meta.py
inigrep/cli.py
inigrep/core.py
inigrep/front.py
inigrep/py.typed
inigrep-0.5.5.dist-info/LICENSE.md
inigrep-0.5.5.dist-info/METADATA
inigrep-0.5.5.dist-info/WHEEL
inigrep-0.5.5.dist-info/top_level.txt
inigrep-0.5.5.dist-info/RECORD
