Metadata-Version: 2.1
Name: inigrep
Version: 0.5.5
Summary: inigrep - grep for (some) INIs
Home-page: https://gitlab.com/vornet/python/python-inigrep
Maintainer-email: Alois Mahdal <netvor+inigrep@vornet.cz>
License: LGPLv2
Classifier: Intended Audience :: Developers
Classifier: Intended Audience :: Information Technology
Classifier: Natural Language :: English
Classifier: Programming Language :: Python
Classifier: Programming Language :: Python :: 3 :: Only
Classifier: Programming Language :: Python :: 3.10
Classifier: Programming Language :: Python :: 3.11
Classifier: Programming Language :: Python :: 3.12
Requires: __VDK_PYPI_REQUIRES__
License-File: LICENSE.md
